havinosh_data_loader/__init__.py
havinosh_data_loader/config.py
havinosh_data_loader/db_utils.py
havinosh_data_loader/exception.py
havinosh_data_loader/logger.py
havinosh_data_loader/process_csv.py
havinosh_data_loader-0.0.3.dist-info/LICENSE
havinosh_data_loader-0.0.3.dist-info/METADATA
havinosh_data_loader-0.0.3.dist-info/WHEEL
havinosh_data_loader-0.0.3.dist-info/entry_points.txt
havinosh_data_loader-0.0.3.dist-info/top_level.txt
havinosh_data_loader-0.0.3.dist-info/RECORD
